MANIFEST.in
setup.py
multichain_mcmc/__init__.py
multichain_mcmc/dream.py
multichain_mcmc/gr_convergence.py
multichain_mcmc/multichain.py
multichain_mcmc/rand_no_replace.c
multichain_mcmc/rand_no_replace.pyx
multichain_mcmc.egg-info/PKG-INFO
multichain_mcmc.egg-info/SOURCES.txt
multichain_mcmc.egg-info/dependency_links.txt
multichain_mcmc.egg-info/requires.txt
multichain_mcmc.egg-info/top_level.txt
multichain_mcmc/examples/example1.py
multichain_mcmc/examples/example2.py
multichain_mcmc/examples/example3.py
multichain_mcmc/examples/example4.py
multichain_mcmc/examples/example5.py
multichain_mcmc/examples/example6.py
multichain_mcmc/examples/example6.pyc
multichain_mcmc/examples/example7.py
multichain_mcmc/examples/model.py
multichain_mcmc/examples/model.pyc
multichain_mcmc/examples/model2.py
multichain_mcmc/examples/model2.pyc
multichain_mcmc/examples/model3.py
multichain_mcmc/examples/model3.pyc
multichain_mcmc/examples/model4.py
multichain_mcmc/examples/model4.pyc
multichain_mcmc/examples/model5.py
multichain_mcmc/examples/model5.pyc
multichain_mcmc/examples/model6.py
multichain_mcmc/examples/model6.pyc
multichain_mcmc/examples/model7.py
multichain_mcmc/examples/model7.pyc
multichain_mcmc/relevant_literature/original matlab DREAM implementation.zip
multichain_mcmc/relevant_literature/terBraak2009VrugtIJNSNS.pdf