Metadata-Version: 1.0
Name: multichain_mcmc
Version: 0.2
Summary: Framework based on PyMC for multichain MCMC algorithms; implementation of DREAM_ZS.
Home-page: pypi.python.org/pypi/multichain_mcmc
Author: John Salvatier
Author-email: jsalvati@u.washington.edu
License: BSD
Platform: UNKNOWN
Classifier: Development Status :: 2 - Pre-Alpha
Classifier: Programming Language :: Python
Classifier: License :: OSI Approved :: BSD License
Classifier: Intended Audience :: Science/Research
Classifier: Topic :: Scientific/Engineering
Classifier: Topic :: Scientific/Engineering :: Mathematics
Classifier: Operating System :: OS Independent
